[{"liveId":"5b77f43a0cf2f04fd1e126ed","title":"张丹丹的直播间","subTitle":"渣哒哒终于出现","picPath":"/mediasource/live/1531489833907ksj5735019.jpg","startTime":1534587962948,"memberId":711745,"liveType":1,"picLoopTime":0,"lrcPath":"/mediasource/live/lrc/5b77f43a0cf2f04fd1e126ed.lrc","streamPath":"http://2519.liveplay.myqcloud.com/live/2519_3630445.flv","screenMode":0,"roomId":"25442929","bwqaVersion":0},{"liveId":"5b77f3c90cf2f04fd1e126ec","title":"黄琬璎的直播间","subTitle":"车车风的窝","picPath":"/mediasource/live/1533998770120m08qBCOFNe.jpg","startTime":1534587849778,"memberId":614755,"liveType":1,"picLoopTime":0,"lrcPath":"/mediasource/live/lrc/5b77f3c90cf2f04fd1e126ec.lrc","streamPath":"http://2519.liveplay.myqcloud.com/live/2519_3630443.flv","screenMode":0,"roomId":"19848043","bwqaVersion":0},{"liveId":"5b77ee060cf2f04fd1e126e9","title":"於佳怡的直播间","subTitle":"～","picPath":"/mediasource/live/1518694285796xyVZoVuen3.jpg","startTime":1534586374223,"memberId":63575,"liveType":1,"picLoopTime":0,"lrcPath":"/mediasource/live/lrc/5b77ee060cf2f04fd1e126e9.lrc","streamPath":"http://2519.liveplay.myqcloud.com/live/2519_3630437.flv","screenMode":0,"roomId":"3866817","bwqaVersion":0}]
