[{"liveId":"5a8c0ea90cf299177c7452ca","title":"沈小爱的直播间","subTitle":"出现？","picPath":"/mediasource/live/1519119970606pTxJv67h0G.png","startTime":1519128233936,"memberId":538697,"liveType":1,"picLoopTime":0,"lrcPath":"/mediasource/live/lrc/5a8c0ea90cf299177c7452ca.lrc","streamPath":"http://2519.liveplay.myqcloud.com/live/2519_3524190.flv","screenMode":0,"roomId":"9470936","bwqaVersion":0},{"liveId":"5a8c0e6a0cf230b94e389e1c","title":"陈问言的直播间","subTitle":"新年快乐啊啊啊","picPath":"/mediasource/live/15020192112383Tz0dDt2vF.JPG","startTime":1519128170220,"memberId":68,"liveType":1,"picLoopTime":0,"lrcPath":"/mediasource/live/lrc/5a8c0e6a0cf230b94e389e1c.lrc","streamPath":"http://2519.liveplay.myqcloud.com/live/2519_3524188.flv","screenMode":0,"roomId":"3870018","bwqaVersion":0},{"liveId":"5a8c0d160cf29aa343fbe11b","title":"汪慕远的直播间","subTitle":"今天的我是英俊霸气多金的李泽言的素颜弟弟","picPath":"/mediasource/live/1519127829792N4D8B6D575.jpg","startTime":1519127830085,"memberId":607524,"liveType":1,"picLoopTime":0,"lrcPath":"/mediasource/live/lrc/5a8c0d160cf29aa343fbe11b.lrc","streamPath":"http://2519.liveplay.myqcloud.com/live/2519_3524186.flv","screenMode":0,"roomId":"18706932","bwqaVersion":0},{"liveId":"5a8c094a0cf299177c7452c8","title":"金莹玥的直播间","subTitle":"火锅","picPath":"/mediasource/live/15160119720566U0RAo22ly.jpg","startTime":1519126858162,"memberId":538735,"liveType":1,"picLoopTime":0,"lrcPath":"/mediasource/live/lrc/5a8c094a0cf299177c7452c8.lrc","streamPath":"http://2519.liveplay.myqcloud.com/live/2519_3524181.flv","screenMode":0,"roomId":"9217644","bwqaVersion":0},{"liveId":"5a8bfded0cf299177c7452c7","title":"郝婧怡的直播间","subTitle":"失踪人口！","picPath":"/mediasource/live/1519123949693h62bC9qr7o.jpg","startTime":1519123949551,"memberId":614753,"liveType":1,"picLoopTime":0,"lrcPath":"/mediasource/live/lrc/5a8bfded0cf299177c7452c7.lrc","streamPath":"http://2519.liveplay.myqcloud.com/live/2519_3524167.flv","screenMode":0,"roomId":"19847208","bwqaVersion":0},{"liveId":"5a8bfa230cf299177c7452c6","title":"张秋怡的直播间","subTitle":"回家路上","picPath":"/mediasource/live/1519122979393X2r3R9KG8i.png","startTime":1519122979278,"memberId":530450,"liveType":1,"picLoopTime":0,"lrcPath":"/mediasource/live/lrc/5a8bfa230cf299177c7452c6.lrc","streamPath":"http://2519.liveplay.myqcloud.com/live/2519_3524166.flv","screenMode":0,"roomId":"8756499","bwqaVersion":0}]
