[{"liveId":"5bd589cf0cf261d802c75717","title":"王嘉瑜的直播间","subTitle":"好卡好卡怎么办(ง•̀_•́)ง","picPath":"/mediasource/live/15401302309417JAUGoq6O0.png","startTime":1540721103364,"memberId":679464,"liveType":1,"picLoopTime":0,"lrcPath":"/mediasource/live/lrc/5bd589cf0cf261d802c75717.lrc","streamPath":"http://2519.liveplay.myqcloud.com/live/2519_3657324.flv","screenMode":0,"roomId":"22537511","bwqaVersion":0},{"liveId":"5bd589510cf261d802c75715","title":"孙馨的直播间","subTitle":"我来啦","picPath":"/mediasource/live/1540547863405HT1k28n79t.jpg","startTime":1540720977921,"memberId":327570,"liveType":1,"picLoopTime":0,"lrcPath":"/mediasource/live/lrc/5bd589510cf261d802c75715.lrc","streamPath":"http://2519.liveplay.myqcloud.com/live/2519_3657320.flv","screenMode":0,"roomId":"3871125","bwqaVersion":0},{"liveId":"5bd5840f0cf23c274367d7e5","title":"曲美霖的直播间","subTitle":"完美底妆","picPath":"/mediasource/live/1540719630853W0SFAii2eV.jpg","startTime":1540719631033,"memberId":711735,"liveType":1,"picLoopTime":0,"lrcPath":"/mediasource/live/lrc/5bd5840f0cf23c274367d7e5.lrc","streamPath":"http://2519.liveplay.myqcloud.com/live/2519_3657312.flv","screenMode":0,"roomId":"25374599","bwqaVersion":0}]
