[{"liveId":"5b335b380cf2dec308557624","title":"魏小燕的直播间","subTitle":"嘿嘿～唠嗑","picPath":"/mediasource/live/1530092344550l7ON5HNV7p.png","startTime":1530092344676,"memberId":707369,"liveType":1,"picLoopTime":0,"lrcPath":"/mediasource/live/lrc/5b335b380cf2dec308557624.lrc","streamPath":"http://2519.liveplay.myqcloud.com/live/2519_3607905.flv","screenMode":0,"roomId":"25723126","bwqaVersion":0},{"liveId":"5b335aad0cf2dec308557623","title":"马凡的直播间","subTitle":"，","picPath":"/mediasource/live/152077689296202E6daX1Aq.png","startTime":1530092205131,"memberId":606343,"liveType":1,"picLoopTime":0,"lrcPath":"/mediasource/live/lrc/5b335aad0cf2dec308557623.lrc","streamPath":"http://2519.liveplay.myqcloud.com/live/2519_3607904.flv","screenMode":0,"roomId":"18047478","bwqaVersion":0},{"liveId":"5b335a9c0cf2dec308557622","title":"谢蕾蕾的直播间","subTitle":"文儿来啦～～","picPath":"/mediasource/live/153009152122954vZXMAmps.jpg","startTime":1530092188785,"memberId":63572,"liveType":1,"picLoopTime":0,"lrcPath":"/mediasource/live/lrc/5b335a9c0cf2dec308557622.lrc","streamPath":"http://2519.liveplay.myqcloud.com/live/2519_3607903.flv","screenMode":0,"roomId":"3871119","bwqaVersion":0},{"liveId":"5b335a8c0cf2b807ce30535f","title":"程戈的直播间","subTitle":"罒ω罒呐答应你们的直播","picPath":"/mediasource/live/1529935614373HaeL23inCt.png","startTime":1530092172539,"memberId":618319,"liveType":1,"picLoopTime":0,"lrcPath":"/mediasource/live/lrc/5b335a8c0cf2b807ce30535f.lrc","streamPath":"http://2519.liveplay.myqcloud.com/live/2519_3607902.flv","screenMode":0,"roomId":"21190935","bwqaVersion":0},{"liveId":"5b3357bd0cf2b807ce30535e","title":"张爱静的电台","subTitle":"是饭点吗？！","picPath":"/mediasource/live/1530091453206bO4B683Sk9.jpg,/mediasource/live/15300914533386fppalLoMi.jpg,/mediasource/live/1530091453422ZTiHObiut0.jpg,/mediasource/live/15300914535118z6m8b5I25.jpg,/mediasource/live/15300914535953NW2A38y77.jpg","startTime":1530091453770,"memberId":480675,"liveType":2,"picLoopTime":30000,"lrcPath":"/mediasource/live/lrc/5b3357bd0cf2b807ce30535e.lrc","streamPath":"http://livepull.48.cn/pocket48/shy48_zhang_aijing_xmnol.flv","screenMode":0,"roomId":"7395696","bwqaVersion":0}]
