[{"liveId":"5b0c10910cf2105290012381","title":"王露皎的直播间","subTitle":"随缘直播诶嘿","picPath":"/mediasource/live/152751720349251g2JRAV3x.jpg","startTime":1527517329587,"memberId":49006,"liveType":1,"picLoopTime":0,"lrcPath":"/mediasource/live/lrc/5b0c10910cf2105290012381.lrc","streamPath":"http://2519.liveplay.myqcloud.com/live/2519_3594034.flv","screenMode":0,"roomId":"3872022","bwqaVersion":0},{"liveId":"5b0c091b0cf210529001237f","title":"黄楚茵的直播间","subTitle":"录完音回来了","picPath":"/mediasource/live/15275082801253AlkZ8F72H.png","startTime":1527515419037,"memberId":607515,"liveType":1,"picLoopTime":0,"lrcPath":"/mediasource/live/lrc/5b0c091b0cf210529001237f.lrc","streamPath":"http://2519.liveplay.myqcloud.com/live/2519_3594027.flv","screenMode":0,"roomId":"18706927","bwqaVersion":0},{"liveId":"5b0c04a60cf2adeb4a4fd97d","title":"陈桂君的直播间","subTitle":"社会人的直播","picPath":"/mediasource/live/1527513494549nUMImaOw4c.jpg","startTime":1527514278704,"memberId":417311,"liveType":1,"picLoopTime":0,"lrcPath":"/mediasource/live/lrc/5b0c04a60cf2adeb4a4fd97d.lrc","streamPath":"http://2519.liveplay.myqcloud.com/live/2519_3594024.flv","screenMode":0,"roomId":"5081868","bwqaVersion":0}]
