[
  {
    "liveId": "345007103084924928",
    "coverPath": "/20190611/15601857014650pVq60j563.jpg",
    "title": "我是Shelly～",
    "liveType": 1,
    "status": 2,
    "ctime": "1560185703296",
    "userInfo": {
      "userId": "63573",
      "nickname": "BEJ48-熊素君",
      "avatar": "/mediasource/avatar/20180608/1528436744438dC7138UwNE.jpg",
      "badge": [],
      "level": 1,
      "isStar": true,
      "friends": "0",
      "followers": "0",
      "teamLogo": "/mediasource/teamLogo2/all/bej48_b.png",
      "signature": "",
      "bgImg": "",
      "vip": false,
      "userRole": 3
    }
  },
  {
    "liveId": "344993797611786240",
    "coverPath": "/20190601/1559363181481WH1bd0bWj1.jpg",
    "title": "今日份的濛濛",
    "liveType": 1,
    "status": 2,
    "ctime": "1560182531024",
    "userInfo": {
      "userId": "874698",
      "nickname": "IDFT-鄢羽蝶",
      "avatar": "/mediasource/avatar/20190410/1554910632819tY6VCI2M8S.jpg",
      "badge": [],
      "level": 1,
      "isStar": true,
      "friends": "0",
      "followers": "0",
      "teamLogo": "/mediasource/teamLogo/all/idft_logo_2.png",
      "signature": "",
      "bgImg": "",
      "vip": false,
      "userRole": 3
    }
  },
  {
    "liveId": "344983259045498880",
    "coverPath": "/20190610/156018001723384IMXSu86h.jpg",
    "title": "啊",
    "liveType": 1,
    "status": 2,
    "ctime": "1560180018434",
    "userInfo": {
      "userId": "327587",
      "nickname": "BEJ48-冯思佳",
      "avatar": "/mediasource/avatar/20180420/1524158237082F67tg21k3I.jpg",
      "badge": [],
      "level": 1,
      "isStar": true,
      "friends": "0",
      "followers": "0",
      "teamLogo": "/mediasource/teamLogo2/all/bej48_e.png",
      "signature": "",
      "bgImg": "/20190416/1555430011580O9sDA7w1gQ.jpg",
      "vip": false,
      "userRole": 3
    }
  }
]
