[
  {
    "liveId": "344644662199128064",
    "coverPath": "/20190610/1560099289534a0D2wC47PW.jpg",
    "title": "喵",
    "liveType": 1,
    "status": 2,
    "ctime": "1560099290655",
    "userInfo": {
      "userId": "677404",
      "nickname": "SNH48-周诗雨",
      "avatar": "/20190605/1559721434750limxgLlGzq.jpg",
      "badge": [],
      "level": 1,
      "isStar": true,
      "friends": "0",
      "followers": "0",
      "teamLogo": "/mediasource/teamLogo2/all/snh48_n2.png",
      "signature": "",
      "bgImg": "",
      "vip": false,
      "userRole": 3
    }
  },
  {
    "liveId": "344637142810300416",
    "coverPath": "/20190610/15600974968897vBg6UZZyp.jpg",
    "title": "🍃",
    "liveType": 1,
    "status": 2,
    "ctime": "1560097497893",
    "userInfo": {
      "userId": "874696",
      "nickname": "GNZ48-叶舒淇",
      "avatar": "/20190529/1559125370465e4c5qMEYR1.jpg",
      "badge": [],
      "level": 1,
      "isStar": true,
      "friends": "0",
      "followers": "0",
      "teamLogo": "/mediasource/teamLogo2/all/gnz48_g.png",
      "signature": "",
      "bgImg": "/20190513/1557683282696A6BmwL4ckJ.jpg",
      "vip": false,
      "userRole": 3
    }
  },
  {
    "liveId": "344643023862042624",
    "coverPath": "/20190610/1560098899082SoM17ak063.jpg",
    "title": "一起全民K歌",
    "liveType": 1,
    "status": 2,
    "ctime": "1560098899403",
    "userInfo": {
      "userId": "607523",
      "nickname": "GNZ48-林芝",
      "avatar": "/mediasource/avatar/20190411/1554993925200TjS97JMUcn.jpg",
      "badge": [],
      "level": 1,
      "isStar": true,
      "friends": "0",
      "followers": "0",
      "teamLogo": "/mediasource/teamLogo2/all/gnz48_g.png",
      "signature": "",
      "bgImg": "/20190417/1555430555922f6DimtXe6H.jpg",
      "vip": false,
      "userRole": 3
    }
  },
  {
    "liveId": "344630561301401600",
    "coverPath": "/20190609/156009592801181143098Dd.jpg",
    "title": "(´｡• ᵕ •｡`) ♡",
    "liveType": 1,
    "status": 2,
    "ctime": "1560095928142",
    "userInfo": {
      "userId": "530452",
      "nickname": "GNZ48-朱怡欣",
      "avatar": "/mediasource/avatar/20190329/1553840220551YNARwA0vpp.jpg",
      "badge": [],
      "level": 1,
      "isStar": true,
      "friends": "0",
      "followers": "0",
      "teamLogo": "/mediasource/teamLogo2/all/gnz48_g.png",
      "signature": "",
      "bgImg": "/20190519/1558203299933D129mbHfCj.jpg",
      "vip": false,
      "userRole": 3
    }
  },
  {
    "liveId": "344633882737184768",
    "coverPath": "/20190610/15600967197932Q275FVDmt.jpg",
    "title": "啵啵啵啵啵",
    "liveType": 1,
    "status": 2,
    "ctime": "1560096720631",
    "userInfo": {
      "userId": "63576",
      "nickname": "GNZ48-阳青颖",
      "avatar": "/mediasource/avatar/20180803/1533267979128J4V9yg1UE7.jpg",
      "badge": [],
      "level": 1,
      "isStar": true,
      "friends": "0",
      "followers": "0",
      "teamLogo": "/mediasource/teamLogo2/all/gnz48_g.png",
      "signature": "",
      "bgImg": "",
      "vip": false,
      "userRole": 3
    }
  },
  {
    "liveId": "344629395452661760",
    "coverPath": "/20190609/1560095647850693Oh409ty.jpg",
    "title": "一会会～",
    "liveType": 1,
    "status": 2,
    "ctime": "1560095650780",
    "userInfo": {
      "userId": "530392",
      "nickname": "BEJ48-张羽涵",
      "avatar": "/mediasource/avatar/20181008/1538995322677x4XyNKiR14.jpg",
      "badge": [],
      "level": 1,
      "isStar": true,
      "friends": "0",
      "followers": "0",
      "teamLogo": "/mediasource/teamLogo2/all/bej48_b.png",
      "signature": "",
      "bgImg": "",
      "vip": false,
      "userRole": 3
    }
  }
]
