[{"liveId":"5a9a922f0cf2fed138578ff5","title":"朱怡欣的直播间","subTitle":"叮咚！您的小祖宗已上线٩(•̤̀ᵕ•̤́","picPath":"/mediasource/live/15200794079453EAItS4zw3.jpg","startTime":1520079407739,"memberId":530452,"liveType":1,"picLoopTime":0,"lrcPath":"/mediasource/live/lrc/5a9a922f0cf2fed138578ff5.lrc","streamPath":"http://2519.liveplay.myqcloud.com/live/2519_3528032.flv","screenMode":0,"roomId":"8752975","bwqaVersion":0},{"liveId":"5a9a8d320cf2bc50772d77cf","title":"谢妮的直播间","subTitle":"☎️","picPath":"/mediasource/live/1519828065998if6E7W779D.jpg","startTime":1520078130889,"memberId":45,"liveType":1,"picLoopTime":0,"lrcPath":"/mediasource/live/lrc/5a9a8d320cf2bc50772d77cf.lrc","streamPath":"http://2519.liveplay.myqcloud.com/live/2519_3528022.flv","screenMode":0,"roomId":"3866803","bwqaVersion":0},{"liveId":"5a9a86b10cf2fed138578ff4","title":"陶菀瑞的直播间","subTitle":"冒泡","picPath":"/mediasource/live/1520007620309CAld4a8v6S.jpg","startTime":1520076465263,"memberId":614736,"liveType":1,"picLoopTime":0,"lrcPath":"/mediasource/live/lrc/5a9a86b10cf2fed138578ff4.lrc","streamPath":"http://2519.liveplay.myqcloud.com/live/2519_3528012.flv","screenMode":0,"roomId":"19835742","bwqaVersion":0}]
