[{"liveId":"5bf7fc820cf23c274367dc1f","title":"李晴的直播间","subTitle":"你来不来。","picPath":"/mediasource/live/1533042179259jh7246hrvW.jpg","startTime":1542978690480,"memberId":480668,"liveType":1,"picLoopTime":0,"lrcPath":"/mediasource/live/lrc/5bf7fc820cf23c274367dc1f.lrc","streamPath":"http://liveplaylk.lvb.eastmoney.com/live/2519_3673485.flv","screenMode":0,"roomId":"7404300","bwqaVersion":0},{"liveId":"5bf7fc000cf23c274367dc1e","title":"康兆薇的直播间","subTitle":"神秘代码-171197732","picPath":"/mediasource/live/1542978560244K7ao0z7Znv.png","startTime":1542978560641,"memberId":867894,"liveType":1,"picLoopTime":0,"lrcPath":"/mediasource/live/lrc/5bf7fc000cf23c274367dc1e.lrc","streamPath":"http://liveplaylk.lvb.eastmoney.com/live/2519_3673484.flv","screenMode":0,"roomId":"58472640","bwqaVersion":0},{"liveId":"5bf7faf20cf23c274367dc1c","title":"赵佳蕊的直播间","subTitle":"下课啦","picPath":"/mediasource/live/15420292916207qv9w7B6tk.jpg","startTime":1542978290109,"memberId":460005,"liveType":1,"picLoopTime":0,"lrcPath":"/mediasource/live/lrc/5bf7faf20cf23c274367dc1c.lrc","streamPath":"http://pl.live.weibo.com/alicdn/5c0a05c68ce45cc0ba4d4bd94e1ec770_wb480.flv","screenMode":0,"roomId":"6486104","bwqaVersion":0},{"liveId":"5bf7fa7d0cf23c274367dc1b","title":"曾佳的直播间","subTitle":"k歌","picPath":"/mediasource/live/15429772164738q038sH2TX.jpg","startTime":1542978173388,"memberId":614741,"liveType":1,"picLoopTime":0,"lrcPath":"/mediasource/live/lrc/5bf7fa7d0cf23c274367dc1b.lrc","streamPath":"http://liveplaylk.lvb.eastmoney.com/live/2519_3673480.flv","screenMode":0,"roomId":"19844104","bwqaVersion":0},{"liveId":"5bf7f46f0cf261d802c7595a","title":"李苏洪的电台","subTitle":"聊天！","picPath":"/mediasource/live/15359931023316Z0VAPGfK1.jpg,/mediasource/live/15429766237222iUzHgIfB9.jpg,/mediasource/live/1542976623862hTlx5JU85O.jpg,/mediasource/live/1542976623999vklfPHzbOe.jpg,/mediasource/live/1542976624115700m4n4w7E.jpg","startTime":1542976623875,"memberId":679462,"liveType":2,"picLoopTime":30000,"lrcPath":"/mediasource/live/lrc/5bf7f46f0cf261d802c7595a.lrc","streamPath":"http://livepull.48.cn/pocket48/shy48_li_suhong_ypskr.flv","screenMode":0,"roomId":"22595556","bwqaVersion":0},{"liveId":"5bf7e8db0cf23c274367dc18","title":"徐晨辰的直播间","subTitle":"重生计划","picPath":"/mediasource/live/1529492908823Kr3Z75Bg2T.jpg","startTime":1542973659658,"memberId":18,"liveType":1,"picLoopTime":0,"lrcPath":"/mediasource/live/lrc/5bf7e8db0cf23c274367dc18.lrc","streamPath":"http://liveplaylk.lvb.eastmoney.com/live/2519_3673442.flv","screenMode":0,"roomId":"3866794","bwqaVersion":0},{"liveId":"5bf7e4d00cf261d802c75958","title":"吴羽霏的直播间","subTitle":"重生计划不重生＃小霏带您看重生计划＃","picPath":"/mediasource/live/1542547686562JW0PQi0f29.png","startTime":1542972624677,"memberId":607591,"liveType":1,"picLoopTime":0,"lrcPath":"/mediasource/live/lrc/5bf7e4d00cf261d802c75958.lrc","streamPath":"http://liveplaylk.lvb.eastmoney.com/live/2519_3673428.flv","screenMode":0,"roomId":"18718159","bwqaVersion":0}]
