[{"liveId":"5bf7f6f70cf283717aba40e4","title":"曾佳的直播间","subTitle":"k歌","picPath":"/mediasource/live/15429772164738q038sH2TX.jpg","startTime":1542977271261,"memberId":614741,"liveType":1,"picLoopTime":0,"lrcPath":"/mediasource/live/lrc/5bf7f6f70cf283717aba40e4.lrc","streamPath":"http://liveplaylk.lvb.eastmoney.com/live/2519_3673469.flv","screenMode":0,"roomId":"19844104","bwqaVersion":0},{"liveId":"5bf7f4ba0cf23c274367dc1a","title":"马凡的直播间","subTitle":"破音歌姬来了","picPath":"/mediasource/live/15365107420136hb0V47J84.png","startTime":1542976698817,"memberId":606343,"liveType":1,"picLoopTime":0,"lrcPath":"/mediasource/live/lrc/5bf7f4ba0cf23c274367dc1a.lrc","streamPath":"http://liveplaylk.lvb.eastmoney.com/live/2519_3673465.flv","screenMode":0,"roomId":"18047478","bwqaVersion":0},{"liveId":"5bf7f46f0cf261d802c7595a","title":"李苏洪的电台","subTitle":"聊天！","picPath":"/mediasource/live/15359931023316Z0VAPGfK1.jpg,/mediasource/live/15429766237222iUzHgIfB9.jpg,/mediasource/live/1542976623862hTlx5JU85O.jpg,/mediasource/live/1542976623999vklfPHzbOe.jpg,/mediasource/live/1542976624115700m4n4w7E.jpg","startTime":1542976623875,"memberId":679462,"liveType":2,"picLoopTime":30000,"lrcPath":"/mediasource/live/lrc/5bf7f46f0cf261d802c7595a.lrc","streamPath":"http://livepull.48.cn/pocket48/shy48_li_suhong_ypskr.flv","screenMode":0,"roomId":"22595556","bwqaVersion":0},{"liveId":"5bf7e9da0cf23c274367dc19","title":"蒋舒婷的直播间","subTitle":"聊天","picPath":"/mediasource/live/154297391445461M2281279.jpg","startTime":1542973914910,"memberId":63561,"liveType":1,"picLoopTime":0,"lrcPath":"/mediasource/live/lrc/5bf7e9da0cf23c274367dc19.lrc","streamPath":"http://liveplaylk.lvb.eastmoney.com/live/2519_3673444.flv","screenMode":0,"roomId":"3869326","bwqaVersion":0},{"liveId":"5bf7e8db0cf23c274367dc18","title":"徐晨辰的直播间","subTitle":"重生计划","picPath":"/mediasource/live/1529492908823Kr3Z75Bg2T.jpg","startTime":1542973659658,"memberId":18,"liveType":1,"picLoopTime":0,"lrcPath":"/mediasource/live/lrc/5bf7e8db0cf23c274367dc18.lrc","streamPath":"http://liveplaylk.lvb.eastmoney.com/live/2519_3673442.flv","screenMode":0,"roomId":"3866794","bwqaVersion":0},{"liveId":"5bf7e4d00cf261d802c75958","title":"吴羽霏的直播间","subTitle":"重生计划不重生＃小霏带您看重生计划＃","picPath":"/mediasource/live/1542547686562JW0PQi0f29.png","startTime":1542972624677,"memberId":607591,"liveType":1,"picLoopTime":0,"lrcPath":"/mediasource/live/lrc/5bf7e4d00cf261d802c75958.lrc","streamPath":"http://liveplaylk.lvb.eastmoney.com/live/2519_3673428.flv","screenMode":0,"roomId":"18718159","bwqaVersion":0}]
