[{"liveId":"5a77d10e0cf2019f6895edb0","title":"熊素君的直播间","subTitle":"十分钟","picPath":"http://www.bej48.com/images/member/zp_20017.jpg?ram=1514204959335","startTime":1517801742680,"memberId":63573,"liveType":1,"picLoopTime":0,"lrcPath":"/mediasource/live/lrc/5a77d10e0cf2019f6895edb0.lrc","streamPath":"http://pl.live.weibo.com/alicdn/ab47e01c7ae3e3370016a8b60b31ef0f_wb480.flv","screenMode":0,"roomId":"3871120","bwqaVersion":1},{"liveId":"5a77cc410cf22cad15707e48","title":"邓倩的直播间","subTitle":"请输入直播宣言","picPath":"/mediasource/live/1516011007631QAEhQy1JQ8.jpg","startTime":1517800513072,"memberId":614750,"liveType":1,"picLoopTime":0,"lrcPath":"/mediasource/live/lrc/5a77cc410cf22cad15707e48.lrc","streamPath":"http://2519.liveplay.myqcloud.com/live/2519_3519717.flv","screenMode":0,"roomId":"19842327","bwqaVersion":1},{"liveId":"5a77cbf90cf289e29b186ece","title":"林舒晴的直播间","subTitle":"嗨各位有人吗","picPath":"/mediasource/live/151780044141297hA4UTrRf.jpg","startTime":1517800441683,"memberId":614756,"liveType":1,"picLoopTime":0,"lrcPath":"/mediasource/live/lrc/5a77cbf90cf289e29b186ece.lrc","streamPath":"http://2519.liveplay.myqcloud.com/live/2519_3519716.flv","screenMode":0,"roomId":"19843742","bwqaVersion":1}]
