[{"liveId":"5c445d660cf23c274367e756","title":"高蔚然的直播间","subTitle":"满城尽带黄金甲","picPath":"/mediasource/live/1547984230162jK6a6IJ2aS.jpg","startTime":1547984230380,"memberId":711726,"liveType":1,"picLoopTime":0,"lrcPath":"/mediasource/live/lrc/5c445d660cf23c274367e756.lrc","streamPath":"http://liveplaylk.lvb.eastmoney.com/live/2519_3695749.flv","screenMode":0,"roomId":"25451672","bwqaVersion":0},{"liveId":"5c445ba80cf283717aba4756","title":"程子钰的直播间","subTitle":"你们期待的仓鼠绝美返图","picPath":"/mediasource/live/15371928436836SIPAgH3w6.png","startTime":1547983784778,"memberId":607510,"liveType":1,"picLoopTime":0,"lrcPath":"/mediasource/live/lrc/5c445ba80cf283717aba4756.lrc","streamPath":"http://liveplaylk.lvb.eastmoney.com/live/2519_3695746.flv","screenMode":0,"roomId":"18711783","bwqaVersion":0},{"liveId":"5c445af50cf23c274367e755","title":"程宇璐的直播间","subTitle":"吃饭没~我们聊聊天可好啊~","picPath":"/mediasource/live/1547385219806269YFMe9tA.png","startTime":1547983605177,"memberId":825969,"liveType":1,"picLoopTime":0,"lrcPath":"/mediasource/live/lrc/5c445af50cf23c274367e755.lrc","streamPath":"http://liveplaylk.lvb.eastmoney.com/live/2519_3695744.flv","screenMode":0,"roomId":"26629356","bwqaVersion":0},{"liveId":"5c4453970cf23c274367e754","title":"王诗蒙的直播间","subTitle":"你好我是王诗蒙，你看这灯多亮，你吃饭没呢","picPath":"/mediasource/live/1547981719620792iMWq9S4.png","startTime":1547981719836,"memberId":459989,"liveType":1,"picLoopTime":0,"lrcPath":"/mediasource/live/lrc/5c4453970cf23c274367e754.lrc","streamPath":"http://alcdn.f01.xiaoka.tv/live/HITALpagTdny-0fl.flv","screenMode":0,"roomId":"6484800","bwqaVersion":0}]
