[{"liveId":"5a509c440cf21c8855fee2ea","title":"李泽亚的直播间","subTitle":"公演完吃烤肉饭 喝neinei","picPath":"/mediasource/live/1515232320057r2AAqF9m9v.png","startTime":1515232320136,"memberId":614729,"liveType":1,"picLoopTime":0,"lrcPath":"/mediasource/live/lrc/5a509c440cf21c8855fee2ea.lrc","streamPath":"http://2519.liveplay.myqcloud.com/live/2519_3502648.flv","screenMode":0},{"liveId":"5a509bf00cf21c8855fee2e9","title":"雷宇霄的直播间","subTitle":"嘻嘻嘻","picPath":"/mediasource/live/15149751725684xliMd55y1.jpg","startTime":1515232236621,"memberId":614728,"liveType":1,"picLoopTime":0,"lrcPath":"/mediasource/live/lrc/5a509bf00cf21c8855fee2e9.lrc","streamPath":"http://2519.liveplay.myqcloud.com/live/2519_3502644.flv","screenMode":0},{"liveId":"5a509b510cf294e8b22f6a6e","title":"王娱博的直播间","subTitle":"超v大佬","picPath":"/mediasource/live/1515053888370RBgSL09fx0.jpg","startTime":1515232081379,"memberId":614740,"liveType":1,"picLoopTime":0,"lrcPath":"/mediasource/live/lrc/5a509b510cf294e8b22f6a6e.lrc","streamPath":"http://2519.liveplay.myqcloud.com/live/2519_3502642.flv","screenMode":0}]
