[
  {
    "liveId": "331167943031066624",
    "coverPath": "/20190503/1556886187535D7GJBM45K5.jpg",
    "title": "十分钟",
    "liveType": 2,
    "status": 2,
    "ctime": "1556886190421",
    "userInfo": {
      "userId": "327597",
      "nickname": "BEJ48-苏杉杉",
      "avatar": "/mediasource/avatar/20180829/1535545582428vP45t8wGVs.jpg",
      "badge": [],
      "level": 1,
      "isStar": true,
      "friends": "0",
      "followers": "0",
      "teamLogo": "/mediasource/teamLogo2/all/bej48_e.png",
      "signature": "",
      "bgImg": "",
      "vip": false,
      "userRole": 3
    }
  },
  {
    "liveId": "331181460505300992",
    "coverPath": "/20190503/15568894115076e5H4T79aM.jpg",
    "title": "☀",
    "liveType": 2,
    "status": 2,
    "ctime": "1556889413238",
    "userInfo": {
      "userId": "623828",
      "nickname": "BEJ48-李娜",
      "avatar": "/mediasource/avatar/20181106/1541483012746C6yccGv9eO.jpg",
      "badge": [],
      "level": 1,
      "isStar": true,
      "friends": "0",
      "followers": "0",
      "teamLogo": "/mediasource/teamLogo2/all/bej48_e.png",
      "signature": "",
      "bgImg": "",
      "vip": false,
      "userRole": 3
    }
  },
  {
    "liveId": "331178272687460352",
    "coverPath": "/20190501/1556725432780oFS2n5glZB.jpg",
    "title": "(灬ºωº灬)",
    "liveType": 1,
    "status": 2,
    "ctime": "1556888653203",
    "userInfo": {
      "userId": "407101",
      "nickname": "BEJ48-陈雅钰",
      "avatar": "/mediasource/avatar/20180608/15284236842127d0f40wTba.jpg",
      "badge": [],
      "level": 1,
      "isStar": true,
      "friends": "0",
      "followers": "0",
      "teamLogo": "/mediasource/teamLogo2/all/bej48_j.png",
      "signature": "",
      "bgImg": "",
      "vip": false,
      "userRole": 3
    }
  },
  {
    "liveId": "331178699533389824",
    "coverPath": "",
    "title": "播一会",
    "liveType": 2,
    "status": 2,
    "ctime": "1556888754539",
    "userInfo": {
      "userId": "874505",
      "nickname": "IDFT-刘宇晴",
      "avatar": "/mediasource/avatar/20190227/1551275776874HFh1XiOA3W.jpg",
      "badge": [],
      "level": 1,
      "isStar": true,
      "friends": "0",
      "followers": "0",
      "teamLogo": "/mediasource/teamLogo/all/idft_logo_2.png",
      "signature": "",
      "bgImg": "/20190415/1555336133714yq6rI1nDYf.jpg",
      "vip": false,
      "userRole": 3
    }
  },
  {
    "liveId": "331184141798019072",
    "coverPath": "/20190503/1556890050487c4u29hhZVd.jpg",
    "title": "新口袋 只求不糊不卡",
    "liveType": 2,
    "status": 2,
    "ctime": "1556890052508",
    "userInfo": {
      "userId": "36",
      "nickname": "SNH48-钱蓓婷",
      "avatar": "/mediasource/avatar/15191826878632L1BWx8088.jpg",
      "badge": [],
      "level": 1,
      "isStar": true,
      "friends": "0",
      "followers": "0",
      "teamLogo": "/mediasource/teamLogo2/all/snh48_s2.png",
      "signature": "",
      "bgImg": "",
      "vip": false,
      "userRole": 3
    }
  }
]
