[{"liveId":"5aa3c7570cf2273cdaee6baa","title":"周洁艺的直播间","subTitle":"三月","picPath":"/mediasource/live/152033952440863Ei0c500l.jpg","startTime":1520682839627,"memberId":652652,"liveType":1,"picLoopTime":0,"lrcPath":"/mediasource/live/lrc/5aa3c7570cf2273cdaee6baa.lrc","streamPath":"http://2519.liveplay.myqcloud.com/live/2519_3531411.flv","screenMode":0,"roomId":"22213635","bwqaVersion":0},{"liveId":"5aa3bf340cf293329e99f29b","title":"张梦慧的直播间","subTitle":"恭候大驾！","picPath":"/mediasource/live/15153330689090ZGmoawde5.jpg","startTime":1520680756458,"memberId":327580,"liveType":1,"picLoopTime":0,"lrcPath":"/mediasource/live/lrc/5aa3bf340cf293329e99f29b.lrc","streamPath":"http://pl.live.weibo.com/alicdn/c8ac2ad84844b3f97ca0a47ace6b9802_wb480.flv","screenMode":0,"roomId":"3868318","bwqaVersion":0},{"liveId":"5aa3bd080cf2273cdaee6ba7","title":"刘菊子的直播间","subTitle":"等外卖","picPath":"/mediasource/live/1520680184415Fj269215Ga.jpg","startTime":1520680200377,"memberId":399664,"liveType":1,"picLoopTime":0,"lrcPath":"/mediasource/live/lrc/5aa3bd080cf2273cdaee6ba7.lrc","streamPath":"http://2519.liveplay.myqcloud.com/live/2519_3531395.flv","screenMode":0,"roomId":"4174442","bwqaVersion":0}]
