[
  {
    "liveId": "349931603517837312",
    "coverPath": "/20190624/1561359795130AUyv5Oa177.jpg",
    "title": "小霓的海底捞自热火锅吃后感",
    "liveType": 1,
    "status": 2,
    "ctime": "1561359795692",
    "userInfo": {
      "userId": "327564",
      "nickname": "GNZ48-陈欣妤",
      "avatar": "/mediasource/avatar/20181031/1540984990227s8GZd9i97q.jpg",
      "badge": [],
      "level": 1,
      "isStar": true,
      "friends": "0",
      "followers": "0",
      "teamLogo": "/mediasource/teamLogo2/all/gnz48_n3.png",
      "signature": "",
      "bgImg": "",
      "vip": false,
      "userRole": 3
    }
  }
]
