[
  {
    "liveId": "361691012673638400",
    "coverPath": "/20190727/1564163455368odjeCYDgaT.jpg",
    "title": "没有小伙伴儿10分钟",
    "liveType": 1,
    "status": 2,
    "ctime": "1564163457314",
    "userInfo": {
      "userId": "327601",
      "nickname": "BEJ48-陈倩楠",
      "avatar": "/mediasource/avatar/20190210/1549802281304XSUvOT4b7q.jpg",
      "badge": [],
      "level": 1,
      "isStar": true,
      "friends": "0",
      "followers": "0",
      "teamLogo": "/mediasource/teamLogo2/all/bej48_e.png",
      "signature": "",
      "bgImg": "",
      "vip": false,
      "userRole": 3
    },
    "liveMode": 0,
    "pictureOrientation": 0
  },
  {
    "liveId": "361692424992264192",
    "coverPath": "/20190727/1564163793422I4Zl1Gbn84.jpg",
    "title": "做个乖宝宝",
    "liveType": 1,
    "status": 2,
    "ctime": "1564163794037",
    "userInfo": {
      "userId": "607521",
      "nickname": "GNZ48-罗可嘉",
      "avatar": "/mediasource/avatar/20190203/1549160918067HhtlQK6Kk5.jpg",
      "badge": [],
      "level": 2,
      "isStar": true,
      "friends": "0",
      "followers": "0",
      "teamLogo": "/mediasource/teamLogo2/all/gnz48_g.png",
      "signature": "",
      "bgImg": "/20190521/15584206154219t0i274i70.jpg",
      "vip": false,
      "userRole": 3
    },
    "liveMode": 0,
    "pictureOrientation": 0
  },
  {
    "liveId": "361694505610317824",
    "coverPath": "/20190727/1564164289801W8OAuSS6AZ.jpg",
    "title": "围观性感小闹直播",
    "liveType": 1,
    "status": 2,
    "ctime": "1564164290096",
    "userInfo": {
      "userId": "327569",
      "nickname": "GNZ48-卢静",
      "avatar": "/20190628/15616607674307R9607YPlx.jpg",
      "badge": [],
      "level": 2,
      "isStar": true,
      "friends": "0",
      "followers": "0",
      "teamLogo": "/mediasource/teamLogo2/all/gnz48_n3.png",
      "signature": "",
      "bgImg": "",
      "vip": false,
      "userRole": 3
    },
    "liveMode": 0,
    "pictureOrientation": 0
  },
  {
    "liveId": "361678989957074944",
    "coverPath": "/20190723/1563857133198yJK6Beo4Yu.jpg",
    "title": "今天又是素颜苗！我会唱孤独与诗了！",
    "liveType": 2,
    "status": 2,
    "ctime": "1564160590875",
    "userInfo": {
      "userId": "874717",
      "nickname": "IDFT-武晓迪",
      "avatar": "/mediasource/avatar/20190320/15530212766396Z27rSj8z0.jpg",
      "badge": [],
      "level": 1,
      "isStar": true,
      "friends": "0",
      "followers": "0",
      "teamLogo": "/mediasource/teamLogo/all/idft_logo_2.png",
      "signature": "",
      "bgImg": "/20190724/15639484387974tpU0X46b8.jpg",
      "vip": false,
      "userRole": 3
    },
    "liveMode": 0,
    "pictureOrientation": 0
  }
]
