[{"liveId":"5c570a4e0cf261d802c76146","title":"林嘉佩的直播间","subTitle":"136.0无聊拼东西(无脸)","picPath":"/mediasource/live/1547031131017hB7bigTMJQ.jpg","startTime":1549208142509,"memberId":63562,"liveType":1,"picLoopTime":0,"lrcPath":"/mediasource/live/lrc/5c570a4e0cf261d802c76146.lrc","streamPath":"http://liveplaylk.lvb.eastmoney.com/live/2519_3701346.flv","screenMode":0,"roomId":"3869327","bwqaVersion":0},{"liveId":"5c5704d30cf261d802c76140","title":"朱小丹的直播间","subTitle":"一起过节","picPath":"/mediasource/live/1548602099800Oev1GFQ207.jpg","startTime":1549206739999,"memberId":677405,"liveType":1,"picLoopTime":0,"lrcPath":"/mediasource/live/lrc/5c5704d30cf261d802c76140.lrc","streamPath":"http://liveplaylk.lvb.eastmoney.com/live/2519_3701338.flv","screenMode":0,"roomId":"25474024","bwqaVersion":0}]
