[{"liveId":"5c14f1180cf23c274367e012","title":"邓倩的直播间","subTitle":"nice～","picPath":"/mediasource/live/1544876312551GLv176K1Hx.jpg","startTime":1544876312802,"memberId":614750,"liveType":1,"picLoopTime":0,"lrcPath":"/mediasource/live/lrc/5c14f1180cf23c274367e012.lrc","streamPath":"http://liveplaylk.lvb.eastmoney.com/live/2519_3680883.flv","screenMode":0,"roomId":"19842327","bwqaVersion":0},{"liveId":"5c14f05c0cf23c274367e011","title":"孙芮的直播间","subTitle":"扒蒜老妹儿","picPath":"/mediasource/live/1533298005921Sw97XDbekR.png","startTime":1544876124574,"memberId":8,"liveType":1,"picLoopTime":0,"lrcPath":"/mediasource/live/lrc/5c14f05c0cf23c274367e011.lrc","streamPath":"http://liveplaylk.lvb.eastmoney.com/live/2519_3680882.flv","screenMode":0,"roomId":"3871095","bwqaVersion":0},{"liveId":"5c14efd70cf261d802c75b25","title":"黄楚茵的直播间","subTitle":"百场已达成（是久违的吃播）","picPath":"/mediasource/live/1544274700679rEi7lj48R9.png","startTime":1544875991144,"memberId":607515,"liveType":1,"picLoopTime":0,"lrcPath":"/mediasource/live/lrc/5c14efd70cf261d802c75b25.lrc","streamPath":"http://liveplaylk.lvb.eastmoney.com/live/2519_3680881.flv","screenMode":0,"roomId":"18706927","bwqaVersion":0},{"liveId":"5c14efbc0cf23c274367e00e","title":"莫寒的直播间","subTitle":"(´｡•ᵕ•｡`)♡","picPath":"/mediasource/live/15448759533576tzbj5LcS6.jpg","startTime":1544875964201,"memberId":35,"liveType":1,"picLoopTime":0,"lrcPath":"/mediasource/live/lrc/5c14efbc0cf23c274367e00e.lrc","streamPath":"http://liveplaylk.lvb.eastmoney.com/live/2519_3680880.flv","screenMode":0,"roomId":"3872010","bwqaVersion":0},{"liveId":"5c14eec30cf261d802c75b24","title":"孙馨的直播间","subTitle":"你的虎虎上线了","picPath":"/mediasource/live/1544875715779d1463Va4to.jpg","startTime":1544875715637,"memberId":327570,"liveType":1,"picLoopTime":0,"lrcPath":"/mediasource/live/lrc/5c14eec30cf261d802c75b24.lrc","streamPath":"http://liveplaylk.lvb.eastmoney.com/live/2519_3680879.flv","screenMode":0,"roomId":"3871125","bwqaVersion":0},{"liveId":"5c14ee160cf23c274367e00b","title":"张雨鑫的直播间","subTitle":"三人食","picPath":"/mediasource/live/1544875541870831ooSgzx9.jpg","startTime":1544875542132,"memberId":5574,"liveType":1,"picLoopTime":0,"lrcPath":"/mediasource/live/lrc/5c14ee160cf23c274367e00b.lrc","streamPath":"http://liveplaylk.lvb.eastmoney.com/live/2519_3680878.flv","screenMode":0,"roomId":"3872017","bwqaVersion":0},{"liveId":"5c14eddd0cf23c274367e00a","title":"钱蓓婷的直播间","subTitle":"三人食","picPath":"/mediasource/live/1511273250814gPJYGAubZU.jpg","startTime":1544875485925,"memberId":36,"liveType":1,"picLoopTime":0,"lrcPath":"/mediasource/live/lrc/5c14eddd0cf23c274367e00a.lrc","streamPath":"http://liveplaylk.lvb.eastmoney.com/live/2519_3680877.flv","screenMode":0,"roomId":"3870016","bwqaVersion":0},{"liveId":"5c14e71b0cf23c274367e008","title":"李瑜璇的直播间","subTitle":"别进来","picPath":"/mediasource/live/1528642404732dY0srif7pD.jpg","startTime":1544873755517,"memberId":614757,"liveType":1,"picLoopTime":0,"lrcPath":"/mediasource/live/lrc/5c14e71b0cf23c274367e008.lrc","streamPath":"http://liveplaylk.lvb.eastmoney.com/live/2519_3680872.flv","screenMode":0,"roomId":"19843744","bwqaVersion":0},{"liveId":"5c14e5f20cf23c274367e007","title":"谢菲菲的直播间","subTitle":"是麋鹿不信你看","picPath":"/mediasource/live/1544873458679ds05ZRv1Lq.jpg","startTime":1544873458853,"memberId":722784,"liveType":1,"picLoopTime":0,"lrcPath":"/mediasource/live/lrc/5c14e5f20cf23c274367e007.lrc","streamPath":"http://liveplaylk.lvb.eastmoney.com/live/2519_3680871.flv","screenMode":0,"roomId":"25749010","bwqaVersion":0},{"liveId":"5c14e5770cf283717aba430a","title":"郝婧怡的直播间","subTitle":"百场啦","picPath":"/mediasource/live/1544800481861xn5WSSj1Y1.jpg","startTime":1544873335234,"memberId":614753,"liveType":1,"picLoopTime":0,"lrcPath":"/mediasource/live/lrc/5c14e5770cf283717aba430a.lrc","streamPath":"http://liveplaylk.lvb.eastmoney.com/live/2519_3680869.flv","screenMode":0,"roomId":"19847208","bwqaVersion":0},{"liveId":"5c14e4c00cf283717aba4309","title":"方琪的直播间","subTitle":"吃晚饭o(｀ω´)o聊聊天","picPath":"/mediasource/live/15448731520932624iSpOQN.jpg","startTime":1544873152311,"memberId":867891,"liveType":1,"picLoopTime":0,"lrcPath":"/mediasource/live/lrc/5c14e4c00cf283717aba4309.lrc","streamPath":"http://liveplaylk.lvb.eastmoney.com/live/2519_3680868.flv","screenMode":0,"roomId":"58481225","bwqaVersion":0},{"liveId":"5c14e4370cf23c274367e006","title":"李晴的直播间","subTitle":"你来不来。","picPath":"/mediasource/live/1533042179259jh7246hrvW.jpg","startTime":1544873015287,"memberId":480668,"liveType":1,"picLoopTime":0,"lrcPath":"/mediasource/live/lrc/5c14e4370cf23c274367e006.lrc","streamPath":"http://liveplaylk.lvb.eastmoney.com/live/2519_3680867.flv","screenMode":0,"roomId":"7404300","bwqaVersion":0},{"liveId":"5c14e0e80cf261d802c75b22","title":"张琼予的直播间","subTitle":"播！","picPath":"/mediasource/live/1544713414986yt5S69Gd4p.jpg","startTime":1544872168199,"memberId":327560,"liveType":1,"picLoopTime":0,"lrcPath":"/mediasource/live/lrc/5c14e0e80cf261d802c75b22.lrc","streamPath":"http://alcdn.f01.xiaoka.tv/live/wBmcEX8bkJTRsD-O.flv","screenMode":0,"roomId":"3872028","bwqaVersion":0}]
