[{"liveId":"5bfa04b00cf261d802c75978","title":"沈梦瑶的直播间","subTitle":"铛铛与我一起吃广州～","picPath":"/mediasource/live/15431118567869d4mh64V0G.jpg","startTime":1543111856513,"memberId":49005,"liveType":1,"picLoopTime":0,"lrcPath":"/mediasource/live/lrc/5bfa04b00cf261d802c75978.lrc","streamPath":"http://pl.live.weibo.com/alicdn/49690fd146af83a16e729134ec49556a_wb480.flv","screenMode":0,"roomId":"3870025","bwqaVersion":0},{"liveId":"5bfa04380cf23c274367dc72","title":"肖文铃的直播间","subTitle":"姐妹们早上好","picPath":"/mediasource/live/15431117363430zAN7eF0Bf.jpg","startTime":1543111736617,"memberId":327573,"liveType":1,"picLoopTime":0,"lrcPath":"/mediasource/live/lrc/5bfa04380cf23c274367dc72.lrc","streamPath":"http://liveplaylk.lvb.eastmoney.com/live/2519_3673853.flv","screenMode":0,"roomId":"3872035","bwqaVersion":0}]
