[{"liveId":"5b3514a30cf2dec308557672","title":"徐慧玲的直播间","subTitle":"我来了！随便播一下","picPath":"/mediasource/live/153020534747778DI45Bx6c.jpg","startTime":1530205347589,"memberId":707372,"liveType":1,"picLoopTime":0,"lrcPath":"/mediasource/live/lrc/5b3514a30cf2dec308557672.lrc","streamPath":"http://2519.liveplay.myqcloud.com/live/2519_3608651.flv","screenMode":0,"roomId":"25529863","bwqaVersion":0},{"liveId":"5b3510760cf2b807ce3053b9","title":"刘佩鑫的直播间","subTitle":"《SAKANA66小时直播挑战》回归1","picPath":"/mediasource/live/1530204278154JNf6NG1eZO.jpg","startTime":1530204278427,"memberId":46,"liveType":1,"picLoopTime":0,"lrcPath":"/mediasource/live/lrc/5b3510760cf2b807ce3053b9.lrc","streamPath":"http://pl.live.weibo.com/alicdn/27b15c2ca4b7c6e8c6ef1b9e0eaf557b_wb480.flv","screenMode":0,"roomId":"3869324","bwqaVersion":0},{"liveId":"5b350cec0cf2b807ce3053b8","title":"王翠菲的直播间","subTitle":"我是你们天使","picPath":"http://www.gnz48.com/images/member/zp_30050.jpg?ram=1523268256395","startTime":1530203372233,"memberId":417324,"liveType":1,"picLoopTime":0,"lrcPath":"/mediasource/live/lrc/5b350cec0cf2b807ce3053b8.lrc","streamPath":"http://pl.live.weibo.com/alicdn/33577d0a659e344657889f18bd0ac977_wb480.flv","screenMode":0,"roomId":"5083254","bwqaVersion":0},{"liveId":"5b3509300cf2b807ce3053b7","title":"徐楚雯的直播间","subTitle":"一小会儿","picPath":"/mediasource/live/15302024165418r164KMs78.jpg","startTime":1530202416780,"memberId":707371,"liveType":1,"picLoopTime":0,"lrcPath":"/mediasource/live/lrc/5b3509300cf2b807ce3053b7.lrc","streamPath":"http://2519.liveplay.myqcloud.com/live/2519_3608640.flv","screenMode":0,"roomId":"25549473","bwqaVersion":0}]
