[{"liveId":"5ba388d70cf2f04fd1e12db4","title":"田姝丽的电台","subTitle":"为了甜有名而开的直播！！！！","picPath":"/mediasource/live/1528719833019h4UW3GBy6x.jpg,/mediasource/live/1527508307700u28ApLQ4XQ.jpg","startTime":1537444055025,"memberId":63571,"liveType":2,"picLoopTime":30000,"lrcPath":"/mediasource/live/lrc/5ba388d70cf2f04fd1e12db4.lrc","streamPath":"http://livepull.48.cn/pocket48/bej48_tian_shuli_yjdaq.flv","screenMode":0,"roomId":"3868309","bwqaVersion":0},{"liveId":"5ba385d30cf2f04fd1e12db3","title":"门秀天的直播间","subTitle":"小学生春游结束啦","picPath":"/mediasource/live/1537443282840ywys7G0SDH.jpg","startTime":1537443283034,"memberId":722782,"liveType":1,"picLoopTime":0,"lrcPath":"/mediasource/live/lrc/5ba385d30cf2f04fd1e12db3.lrc","streamPath":"http://2519.liveplay.myqcloud.com/live/2519_3641717.flv","screenMode":0,"roomId":"25807784","bwqaVersion":0}]
