[
  {
    "liveId": "349610856589103104",
    "coverPath": "/20190623/156128332262159ft3o980H.jpg",
    "title": "☀️",
    "liveType": 1,
    "status": 2,
    "ctime": "1561283323409",
    "userInfo": {
      "userId": "327593",
      "nickname": "BEJ48-李诗彦",
      "avatar": "/mediasource/avatar/20180908/1536399163968cZv7DCf8k4.jpg",
      "badge": [],
      "level": 1,
      "isStar": true,
      "friends": "0",
      "followers": "0",
      "teamLogo": "/mediasource/teamLogo2/all/bej48_e.png",
      "signature": "",
      "bgImg": "",
      "vip": false,
      "userRole": 3
    }
  },
  {
    "liveId": "349612796869939200",
    "coverPath": "/20190623/1561283785704dKJiW89y57.jpg",
    "title": "晚上好ヾ(Ő∀Ő)ﾉ",
    "liveType": 1,
    "status": 2,
    "ctime": "1561283786070",
    "userInfo": {
      "userId": "327591",
      "nickname": "BEJ48-李梓",
      "avatar": "/mediasource/avatar/20180617/1529172122894zh6k61ung7.jpg",
      "badge": [],
      "level": 1,
      "isStar": true,
      "friends": "0",
      "followers": "0",
      "teamLogo": "/mediasource/teamLogo2/all/bej48_e.png",
      "signature": "",
      "bgImg": "",
      "vip": false,
      "userRole": 3
    }
  }
]
