[{"liveId":"5c417ca30cf283717aba471d","title":"林芝的直播间","subTitle":"这是一个化妆直播","picPath":"/mediasource/live/1547391277783MceJxjaT9E.jpg","startTime":1547795619379,"memberId":607523,"liveType":1,"picLoopTime":0,"lrcPath":"/mediasource/live/lrc/5c417ca30cf283717aba471d.lrc","streamPath":"http://liveplaylk.lvb.eastmoney.com/live/2519_3695091.flv","screenMode":0,"roomId":"18706930","bwqaVersion":0},{"liveId":"5c417a200cf283717aba471b","title":"臧聪的直播间","subTitle":"jiang~","picPath":"/mediasource/live/1547794976630oE1Pl96UQF.jpg","startTime":1547794976756,"memberId":530381,"liveType":1,"picLoopTime":0,"lrcPath":"/mediasource/live/lrc/5c417a200cf283717aba471b.lrc","streamPath":"http://liveplaylk.lvb.eastmoney.com/live/2519_3695082.flv","screenMode":0,"roomId":"8757311","bwqaVersion":0}]
