[{"liveId":"5af449110cf2392c4b1c2241","title":"张羽涵的直播间","subTitle":"啊啊啊啊啊","picPath":"/mediasource/live/151911041829635IjF1X7ph.png","startTime":1525958929032,"memberId":530392,"liveType":1,"picLoopTime":0,"lrcPath":"/mediasource/live/lrc/5af449110cf2392c4b1c2241.lrc","streamPath":"http://2519.liveplay.myqcloud.com/live/2519_3579138.flv","screenMode":0,"roomId":"8755740","bwqaVersion":0},{"liveId":"5af447730cf27c5d80eaa38c","title":"吴学雨的直播间","subTitle":"哈哈哈哈哈哈哈哈","picPath":"/mediasource/live/1525958265514thy2jIS5ph.jpg","startTime":1525958515087,"memberId":614761,"liveType":1,"picLoopTime":0,"lrcPath":"/mediasource/live/lrc/5af447730cf27c5d80eaa38c.lrc","streamPath":"http://2519.liveplay.myqcloud.com/live/2519_3579134.flv","screenMode":0,"roomId":"19843746","bwqaVersion":0},{"liveId":"5af442910cf2392c4b1c223f","title":"董思佳的直播间","subTitle":"(/ω＼)","picPath":"/mediasource/live/1525957265214DTdq6sbdh1.jpg","startTime":1525957265467,"memberId":480656,"liveType":1,"picLoopTime":0,"lrcPath":"/mediasource/live/lrc/5af442910cf2392c4b1c223f.lrc","streamPath":"http://2519.liveplay.myqcloud.com/live/2519_3579124.flv","screenMode":0,"roomId":"7393787","bwqaVersion":0},{"liveId":"5af441ef0cf2392c4b1c223e","title":"朱敏的电台","subTitle":"晚上好","picPath":"/mediasource/live/15246606698888INa6h49y9.jpg,/mediasource/live/1525957102707yuChOQL704.jpg","startTime":1525957103047,"memberId":679467,"liveType":2,"picLoopTime":30000,"lrcPath":"/mediasource/live/lrc/5af441ef0cf2392c4b1c223e.lrc","streamPath":"http://livepull.48.cn/pocket48/shy48_zhu_min_ifheh.flv","screenMode":0,"roomId":"22643829","bwqaVersion":0},{"liveId":"5af440c60cf2392c4b1c223d","title":"冯晓菲的直播间","subTitle":"。","picPath":"/mediasource/live/10ba1208-b0aa-4553-a86b-0203b121f482.jpg","startTime":1525956806148,"memberId":6432,"liveType":1,"picLoopTime":0,"lrcPath":"/mediasource/live/lrc/5af440c60cf2392c4b1c223d.lrc","streamPath":"http://2519.liveplay.myqcloud.com/live/2519_3579116.flv","screenMode":0,"roomId":"3868300","bwqaVersion":0},{"liveId":"5af43e9e0cf2392c4b1c223c","title":"李晴的直播间","subTitle":"晚上好","picPath":"/mediasource/live/1525951919382a37Jfk3tG6.jpg","startTime":1525956254955,"memberId":480668,"liveType":1,"picLoopTime":0,"lrcPath":"/mediasource/live/lrc/5af43e9e0cf2392c4b1c223c.lrc","streamPath":"http://2519.liveplay.myqcloud.com/live/2519_3579104.flv","screenMode":0,"roomId":"7404300","bwqaVersion":0},{"liveId":"5af43be10cf2392c4b1c223a","title":"高志娴的直播间","subTitle":"不来白不来","picPath":"/mediasource/live/1525955553025F1i3K2PV8j.jpg","startTime":1525955553551,"memberId":480665,"liveType":1,"picLoopTime":0,"lrcPath":"/mediasource/live/lrc/5af43be10cf2392c4b1c223a.lrc","streamPath":"http://pl.live.weibo.com/alicdn/fe98407bbade74d0f7ef1a8b88a1bfab_wb480.flv","screenMode":0,"roomId":"7403679","bwqaVersion":0}]
